ipregistry/__init__.py
ipregistry/cache.py
ipregistry/core.py
ipregistry/json.py
ipregistry/model.py
ipregistry/request.py
ipregistry/util.py
ipregistry-4.0.0.dist-info/LICENSE.txt
ipregistry-4.0.0.dist-info/METADATA
ipregistry-4.0.0.dist-info/WHEEL
ipregistry-4.0.0.dist-info/RECORD
