Metadata-Version: 2.1
Name: ipregistry
Version: 4.0.0
Summary: Official Python library for Ipregistry
Home-page: https://ipregistry.co
License: Apache-2.0
Keywords: ipinfo,ipregistry,ip-address,ip-data,ip-geolocation,threat-detection,user-agent-parsing
Author: Ipregistry Team
Author-email: support@ipregistry.co
Requires-Python: >=3.8
Classifier: License :: OSI Approved :: Apache Software License
Classifier: Programming Language :: Python :: 3
Classifier: Programming Language :: Python :: 3.8
Classifier: Programming Language :: Python :: 3.9
Classifier: Programming Language :: Python :: 3.10
Classifier: Programming Language :: Python :: 3.11
Classifier: Programming Language :: Python :: 3.12
Requires-Dist: cachetools (>=5.3.3,<6.0.0)
Requires-Dist: pydantic (>=2.7.3,<3.0.0)
Requires-Dist: requests (>=2.32.3,<3.0.0)
Requires-Dist: tenacity (>=8.3.0,<9.0.0)
Project-URL: Repository, https://github.com/ipregistry/ipregistry-python
